hatch_demo/__about__.py
hatch_demo/__init__.py
hatch_demo-1rc0.dist-info/LICENSE.txt
hatch_demo-1rc0.dist-info/METADATA
hatch_demo-1rc0.dist-info/WHEEL
hatch_demo-1rc0.dist-info/entry_points.txt
hatch_demo-1rc0.dist-info/RECORD
